idpmodem/__init__.py
idpmodem/asyncio/__init__.py
idpmodem/asyncio/atcommand.py
idpmodem/asyncio/atcommand_async.py
idpmodem/asyncio/modem.py
idpmodem/aterror.py
idpmodem/codecs/__init__.py
idpmodem/codecs/common_mdf.py
idpmodem/codecs/common_message_format/__init__.py
idpmodem/codecs/common_message_format/base.py
idpmodem/codecs/common_message_format/constants.py
idpmodem/codecs/common_message_format/fields/__init__.py
idpmodem/codecs/common_message_format/fields/array_field.py
idpmodem/codecs/common_message_format/fields/base_field.py
idpmodem/codecs/common_message_format/fields/boolean_field.py
idpmodem/codecs/common_message_format/fields/data_field.py
idpmodem/codecs/common_message_format/fields/enum_field.py
idpmodem/codecs/common_message_format/fields/helpers.py
idpmodem/codecs/common_message_format/fields/integer_field.py
idpmodem/codecs/common_message_format/fields/string_field.py
idpmodem/codecs/common_message_format/message_definitions.py
idpmodem/codecs/common_message_format/messages.py
idpmodem/codecs/common_message_format/services.py
idpmodem/constants.py
idpmodem/crcxmodem.py
idpmodem/helpers.py
idpmodem/location.py
idpmodem/propertycache.py
idpmodem/s_registers.py
idpmodem/threaded/__init__.py
idpmodem/threaded/atcommand.py
idpmodem/threaded/modem.py
idpmodem-2.3.9.dist-info/LICENSE
idpmodem-2.3.9.dist-info/WHEEL
idpmodem-2.3.9.dist-info/METADATA
idpmodem-2.3.9.dist-info/RECORD
