Metadata-Version: 2.1
Name: idpmodem
Version: 2.3.9
Summary: A library for interfacing with an Inmarsat IsatData Pro satellite IoT modem using serial AT commands.
Home-page: https://github.com/inmarsat-enterprise.com/idpmodem
License: Apache2.0
Keywords: satellite,iot
Author: geoffbrucepayne
Author-email: geoff.bruce-payne@inmarsat.com
Requires-Python: >=3.8,<4.0
Classifier: License :: Other/Proprietary License
Classifier: Programming Language :: Python :: 3
Classifier: Programming Language :: Python :: 3.10
Classifier: Programming Language :: Python :: 3.8
Classifier: Programming Language :: Python :: 3.9
Requires-Dist: aioserial (==1.3.0)
Requires-Dist: pyserial (>=3.5,<4.0)
Requires-Dist: pyserial-asyncio (>=0.6,<0.7)
Project-URL: Repository, https://github.com/inmarsat-enterprise.com/idpmodem
